{
    "EasyAntiCheat": "https://www.easy.ac/en-US",
    "FACEIT AC": "https://www.faceit.com/en/anti-cheat",
    "GameGuard": "https://gameguard.ac",
    "Discord": "https://discord.com",
    "DeepL": "https://www.deepl.com",
    "Element": "https://element.io",
    "Guilded": "https://www.guilded.gg",
    "Signal": "https://signal.org",
    "Telegram": "https://desktop.telegram.org",
    "Thunderbird": "https://www.thunderbird.net",
    "MAX": "https://max.ru",
    "7-Zip": "https://www.7-zip.org/download.html",
    "WinRaR": "https://www.win-rar.com/predownload.html",
    "AAF Optimus DCH Audio": "https://github.com/AAFOptimus/AAFFamilyDCHAudio",
    "ASIO4ALL v2": "https://asio4all.org/about/download-asio4all",
    "Alsa": "https://en.wikipedia.org/wiki/Advanced_Linux_Sound_Architecture",
    "FL Studio": "https://www.image-line.com/fl-studio-download",
    "SoundWire Server": "https://georgielabs.net",
    "Cassettle": "https://gitlab.gnome.org/Rirusha/Cassette",
    "Spotify": "https://open.spotify.com/download",
    "Yandex Music": "https://music.yandex.ru/download",
    "Brave Browser": "https://brave.com/download",
    "Edge": "https://www.microsoft.com/edge",
    "Google Chrome": "https://www.google.com/intl/en/chrome",
    "LibreWolf": "https://librewolf.net/installation",
    "Mozilla Firefox": "https://www.mozilla.org/firefox/new",
    "Opera GX": "https://www.opera.com/download",
    "Vivaldi": "https://vivaldi.com/download",
    "ATLauncher": "https://atlauncher.com/downloads",
    "Badlion Client": "https://www.badlion.net/minecraft-client",
    "Cristalix": "https://cristalix.gg",
    "CubixWorld": "https://cubixworld.net/start",
    "CurseForge": "https://www.curseforge.com/download/app",
    "GribLand": "https://gribland.net/#start",
    "LoliLand": "https://loliland.ru/ru/start",
    "Lunar Client": "https://www.lunarclient.com/download",
    "MCSkill": "https://mcskill.net/start",
    "McLaunch": "https://github.com/mclaunch/mclaunch",
    "Minecraft": "https://www.minecraft.net/ru-ru/about-minecraft",
    "Modrinth": "https://modrinth.com/app",
    "MultiMC": "https://multimc.org/#Download",
    "PolyMC": "https://polymc.org/download",
    "PrismLauncher": "https://prismlauncher.org/download/windows",
    "Tecknix Client": "https://tecknix.com/download.html",
    "SimpleMinecraft": "https://simpleminecraft.ru/start.html",
    "X Minecraft Launcher": "https://xmcl.app",
    "HiAlgo Boost": "https://www.hialgo.com",
    "Mem Reduct": "https://github.com/henrypp/memreduct",
    "Winutil": "https://github.com/ChrisTitusTech/winutil",
    "ССleaner": "https://www.ccleaner.com",
    "1Password": "https://1password.com/",
    "KeePass 2": "https://keepass.info/download.html",
    "KeePassXC": "https://keepassxc.org/download",
    "Future Client": "https://futureclient.net",
    "Cheat Engine": "https://www.cheatengine.org/downloads.php",
    "ExecHack": "https://c.exechack.cc",
    "RusherHack": "https://rusherhack.org",
    "Fatality": "https://fatality.win",
    "INTERIUM": "https://ru.interium.ooo",
    "Krnl": "https://wearedevs.net/d/Krnl",
    "OneTap": "https://www.onetap.com",
    "Vape Client": "https://www.vape.gg",
    "Weave": "https://weave.su",
    "Bit Monero": "https://www.getmonero.org/downloads",
    "Exodus Crypto Wallet": "https://www.exodus.com/download",
    "Wasabi Wallet": "https://wasabiwallet.io",
    "Jdk": "https://www.oracle.com/java/technologies/downloads",
    "GTK": "https://www.gtk.org",
    "Ghidra": "https://github.com/NationalSecurityAgency/ghidra",
    "Gradle": "https://gradle.org",
    "BoxedAppPacker": "https://www.boxedapp.com/boxedapppacker/download.html",
    "Docker": "https://www.docker.com/products/docker-desktop",
    "DotNet": "https://dotnet.microsoft.com/en-us/download",
    "Enigma Virtual Box": "https://enigmaprotector.com/en/downloads.html",
    "Git": "https://git-scm.com/downloads",
    "GitHub Desktop": "https://desktop.github.com/download",
    "Go Language": "https://go.dev/doc/install",
    "IDA Pro": "https://hex-rays.com/ida-pro",
    "Inno Setup 6": "https://jrsoftware.org/isdl.php#stable",
    "Java": "https://www.java.com/download",
    "MCCreator": "https://mcreator.net/download",
    "MinGW": "https://www.mingw-w64.org/downloads",
    "Node JS": "https://nodejs.org/en/download",
    "Postman": "https://www.postman.com/downloads",
    "Python": "https://www.python.org/downloads",
    "Recaf": "https://github.com/Col-E/Recaf",
    "Rust Language": "https://www.rust-lang.org/tools/install",
    "Unity Hub": "https://unity.com/download",
    "IObit Driver Booster": "https://ru.iobit.com/driver-booster.php",
    "LGHUB": "https://www.logitechg.com/en-us/innovation/g-hub.html",
    "NVIDIA App": "https://www.nvidia.com/en-us/software/nvidia-app",
    "NVIDIA": "https://www.nvidia.com",
    "VulcanRT": "https://vulkan.lunarg.com/sdk/home",
    "BlueStacks": "https://www.bluestacks.com",
    "BlueStacks 5": "https://www.bluestacks.com",
    "Gameloop": "https://www.gameloop.com",
    "Memu": "https://www.memuplay.com/download.html",
    "Nox": "https://bignox.com/nox-app-player",
    "Lutris": "https://lutris.net/downloads",
    "Garry's mod": "https://store.steampowered.com/app/4000/Garrys_Mod",
    "Hearts of Iron IV": "https://store.steampowered.com/app/394360/Hearts_of_Iron_IV",
    "Arizona Games Launcher": "https://arizona-rp.com/#how-to-play",
    "Counter-Strike Global Offensive": "https://store.steampowered.com/app/730/CounterStrike_2",
    "Dota 2": "https://www.dota2.com/home",
    "Electronic Arts Desktop": "https://www.ea.com/ea-app",
    "Epic Games Launcher": "https://store.epicgames.com/en-US/download",
    "Lords Mobile": "https://lordsmobile.igg.com/pc",
    "Melissia Games Launcher": "https://melissia.games",
    "Osu": "https://osu.ppy.sh/home/download",
    "Roblox": "https://www.roblox.com/download",
    "Rust": "https://store.steampowered.com/app/252490/Rust",
    "Steam": "https://store.steampowered.com/about",
    "Steam Proton": "https://github.com/ValveSoftware/Proton",
    "Terraria": "https://terraria.org",
    "The Powder Toy": "https://powdertoy.co.uk",
    "Unturned": "https://store.steampowered.com/app/304930/Unturned",
    "VK GameCenter": "https://vkplay.ru/about/?from=gamecenter",
    "RimWorld": "https://store.steampowered.com/app/294100/RimWorld",
    "Winetricks": "https://github.com/Winetricks/winetricks",
    "Oxygen Not Included": "https://store.steampowered.com/app/457140/Oxygen_Not_Included",
    "ImageGlass": "https://imageglass.org",
    "InkSpace": "https://inkscape.org",
    "Magpie": "https://github.com/Blinue/Magpie",
    "Microsoft Lobe": "https://github.com/orgs/lobe",
    "ShareX": "https://getsharex.com/downloads",
    "Tonfotos Telegram Connector": "https://tonfotos.com",
    "4uKey for Android": "https://www.tenorshare.ru/products/android-password-reset-tool.html",
    "Gpg4win": "https://www.gpg4win.org",
    "I2P": "https://geti2p.net/download",
    "IObit Malware Fighter": "https://www.iobit.com/en/malware-fighter.php",
    "NetLimiter": "https://www.netlimiter.com/download",
    "OONI Probe": "https://ooni.org/install",
    "Panda Security": "https://www.pandasecurity.com",
    "Process Hacker 2": "https://systeminformer.sourceforge.io/downloads",
    "Process Lasso": "https://bitsum.com",
    "Sandboxie+": "https://sandboxie-plus.com",
    "SystemInformer": "https://systeminformer.com/downloads",
    "VirtualBox": "https://www.virtualbox.org/wiki/Downloads",
    "Zapret": "https://github.com/bol-van/zapret",
    "Cursor": "https://www.cursor.com/downloads",
    "JetBrains": "https://www.jetbrains.com/?var=1",
    "LM Studio": "https://lmstudio.ai/download",
    "LazyVim": "https://www.lazyvim.org/installation",
    "LibreOffice": "https://www.libreoffice.org/download/download-libreoffice",
    "NeoVim": "https://github.com/neovim/neovim/blob/master/INSTALL.md",
    "Notepad++": "https://notepad-plus-plus.org/downloads",
    "Sublime Text": "https://www.sublimetext.com/download",
    "VS Code": "https://code.visualstudio.com/download",
    "Gperf": "https://github.com/jwinarske/gperf",
    "Pcre": "https://www.pcre.org",
    "Tribler": "https://www.tribler.org/download.html",
    "qBittorrent": "https://www.qbittorrent.org/download",
    "MiniBin": "https://github.com/king-tri-ton/minibin",
    "PowerToys": "https://github.com/microsoft/PowerToys",
    "Amnezia VPN": "https://github.com/amnezia-vpn/amnezia-client",
    "Amnezia WG": "https://docs.amnezia.org/ru/documentation/amnezia-wg",
    "CloudFlare": "https://one.one.one.one",
    "PlanetVPN": "https://freevpnplanet.com",
    "Radmin VPN": "https://www.radmin-vpn.com/help/code56",
    "UrbanVPN": "https://www.urban-vpn.com",
    "Windscribe": "https://windscribe.com/features/windows",
    "iTop VPN": "https://www.itopvpn.com",
    "AVCLabs Video Enhancer AI": "https://www.avclabs.com/video-enhancer-ai.html",
    "HandBrake": "https://handbrake.fr/downloads.php",
    "OBS Studio": "https://obsproject.com/download",
    "Rave": "https://rave.io",
    "Topaz Video AI": "https://www.topazlabs.com/topaz-video-ai",
    "VLC": "https://www.videolan.org/vlc",
    "iTop Screen Recorder": "https://recorder.itopvpn.com",
    "Yay": "https://github.com/Jguer/yay",
    "Chocolatey": "https://chocolatey.org/install",
    "Scoop": "https://scoop.sh",
    "WinGet": "https://github.com/microsoft/winget-cli",
    "pipx": "https://github.com/pypa/pipx",
    "ImgBurn": "https://www.imgburn.com/index.php?act=download",
    "CachyOS": "https://cachyos.org",
    "Linux": "https://www.kernel.org",
    "OneDrive": "https://www.microsoft.com/microsoft-365/onedrive/online-cloud-storage",
    "Windows": "https://www.microsoft.com/download/windows",
    "Windows Defender": "https://www.microsoft.com/download/windows"
}